wigglystuff/__init__.py
wigglystuff/cell_tour.py
wigglystuff/chart_puck.py
wigglystuff/chart_select.py
wigglystuff/color_picker.py
wigglystuff/copy_to_clipboard.py
wigglystuff/driver_tour.py
wigglystuff/edge_draw.py
wigglystuff/env_config.py
wigglystuff/gamepad.py
wigglystuff/html.py
wigglystuff/keystroke.py
wigglystuff/matrix.py
wigglystuff/paint.py
wigglystuff/pulsar_chart.py
wigglystuff/slider2d.py
wigglystuff/sortable_list.py
wigglystuff/talk.py
wigglystuff/tangle.py
wigglystuff/text_compare.py
wigglystuff/three_widget.py
wigglystuff/utils.py
wigglystuff/webcam_capture.py
wigglystuff/static/2dslider.js
wigglystuff/static/chart-puck.js
wigglystuff/static/chart-select.css
wigglystuff/static/chart-select.js
wigglystuff/static/colorpicker.js
wigglystuff/static/copybutton.css
wigglystuff/static/copybutton.js
wigglystuff/static/driver-tour.css
wigglystuff/static/driver-tour.js
wigglystuff/static/edgedraw.css
wigglystuff/static/edgedraw.js
wigglystuff/static/env-config.css
wigglystuff/static/env-config.js
wigglystuff/static/gamepad-widget.js
wigglystuff/static/keystroke-widget.js
wigglystuff/static/keystroke.css
wigglystuff/static/matrix.css
wigglystuff/static/matrix.js
wigglystuff/static/paint.css
wigglystuff/static/paint.js
wigglystuff/static/pulsar-chart.css
wigglystuff/static/pulsar-chart.js
wigglystuff/static/sortable-list.css
wigglystuff/static/sortable-list.js
wigglystuff/static/talk-widget.css
wigglystuff/static/talk-widget.js
wigglystuff/static/tangle-choice.js
wigglystuff/static/tangle-select.js
wigglystuff/static/tangle-slider.js
wigglystuff/static/text-compare.css
wigglystuff/static/text-compare.js
wigglystuff/static/three-widget.css
wigglystuff/static/three-widget.js
wigglystuff/static/webcam-capture.css
wigglystuff/static/webcam-capture.js
wigglystuff-0.2.19.dist-info/METADATA
wigglystuff-0.2.19.dist-info/WHEEL
wigglystuff-0.2.19.dist-info/licenses/LICENSE
wigglystuff-0.2.19.dist-info/RECORD
