Metadata-Version: 2.4
Name: wigglystuff
Version: 0.2.19
Summary: Collection of Anywidget Widgets
Author: Vincent D. Warmerdam
License: MIT License
License-File: LICENSE
Classifier: Intended Audience :: Developers
Classifier: Intended Audience :: Science/Research
Classifier: License :: OSI Approved :: MIT License
Classifier: Programming Language :: Python :: 3
Classifier: Topic :: Scientific/Engineering
Requires-Python: >=3.10
Requires-Dist: anywidget>=0.9.2
Requires-Dist: numpy
Requires-Dist: pillow
Provides-Extra: docs
Requires-Dist: altair>=6.0.0; extra == 'docs'
Requires-Dist: black>=24.8.0; extra == 'docs'
Requires-Dist: marimo>=0.18.0; extra == 'docs'
Requires-Dist: mike>=2.1.0; extra == 'docs'
Requires-Dist: mkdocs-git-revision-date-localized-plugin>=1.2.6; extra == 'docs'
Requires-Dist: mkdocs-include-markdown-plugin>=6.2.1; extra == 'docs'
Requires-Dist: mkdocs-jupyter>=0.25.0; extra == 'docs'
Requires-Dist: mkdocs-material>=9.5.0; extra == 'docs'
Requires-Dist: mkdocs-section-index>=0.3.6; extra == 'docs'
Requires-Dist: mkdocstrings[python]>=0.25.1; extra == 'docs'
Requires-Dist: mohtml>=0.1.11; extra == 'docs'
Requires-Dist: pandas>=2.3.3; extra == 'docs'
Requires-Dist: polars>=1.36.1; extra == 'docs'
Provides-Extra: test
Requires-Dist: matplotlib>=3.0; extra == 'test'
Requires-Dist: pytest>=8.3.3; extra == 'test'
Requires-Dist: scikit-learn>=1.0; extra == 'test'
Provides-Extra: test-browser
Requires-Dist: marimo>=0.18.0; extra == 'test-browser'
Requires-Dist: pytest-playwright>=0.6.2; extra == 'test-browser'
Requires-Dist: pytest>=8.3.3; extra == 'test-browser'
